erk_shared/__init__.py
erk_shared/debug.py
erk_shared/debug_timing.py
erk_shared/env.py
erk_shared/impl_folder.py
erk_shared/issue_workflow.py
erk_shared/naming.py
erk_shared/non_ideal_state.py
erk_shared/plan_utils.py
erk_shared/subprocess_utils.py
erk_shared/worker_impl_folder.py
erk_shared/branch_manager/__init__.py
erk_shared/branch_manager/abc.py
erk_shared/branch_manager/factory.py
erk_shared/branch_manager/fake.py
erk_shared/branch_manager/git.py
erk_shared/branch_manager/graphite.py
erk_shared/branch_manager/types.py
erk_shared/config/__init__.py
erk_shared/config/schema.py
erk_shared/context/__init__.py
erk_shared/context/context.py
erk_shared/context/factories.py
erk_shared/context/helpers.py
erk_shared/context/testing.py
erk_shared/context/types.py
erk_shared/core/__init__.py
erk_shared/core/claude_executor.py
erk_shared/core/codespace_registry.py
erk_shared/core/fakes.py
erk_shared/core/plan_list_service.py
erk_shared/core/script_writer.py
erk_shared/core/typing_utils.py
erk_shared/gateway/__init__.py
erk_shared/gateway/browser/__init__.py
erk_shared/gateway/browser/abc.py
erk_shared/gateway/browser/fake.py
erk_shared/gateway/browser/real.py
erk_shared/gateway/clipboard/__init__.py
erk_shared/gateway/clipboard/abc.py
erk_shared/gateway/clipboard/fake.py
erk_shared/gateway/clipboard/real.py
erk_shared/gateway/codespace/__init__.py
erk_shared/gateway/codespace/abc.py
erk_shared/gateway/codespace/fake.py
erk_shared/gateway/codespace/real.py
erk_shared/gateway/completion/__init__.py
erk_shared/gateway/completion/abc.py
erk_shared/gateway/completion/fake.py
erk_shared/gateway/completion/real.py
erk_shared/gateway/console/__init__.py
erk_shared/gateway/console/abc.py
erk_shared/gateway/console/fake.py
erk_shared/gateway/console/real.py
erk_shared/gateway/erk_installation/__init__.py
erk_shared/gateway/erk_installation/abc.py
erk_shared/gateway/erk_installation/fake.py
erk_shared/gateway/erk_installation/real.py
erk_shared/gateway/graphite/__init__.py
erk_shared-0.7.0.dist-info/METADATA
erk_shared-0.7.0.dist-info/WHEEL
erk_shared-0.7.0.dist-info/RECORD
