Metadata-Version: 2.4
Name: erk-shared
Version: 0.7.0
Summary: Shared utilities and interfaces for erk and erk-kits
Requires-Python: >=3.11
Requires-Dist: click>=8.1.7
Requires-Dist: httpx>=0.27.0
Requires-Dist: python-frontmatter>=1.0.0
Requires-Dist: pyyaml>=6.0
Requires-Dist: tomlkit>=0.12.0
